torch_sim/__init__.py
torch_sim/autobatching.py
torch_sim/constraints.py
torch_sim/elastic.py
torch_sim/integrators/__init__.py
torch_sim/integrators/md.py
torch_sim/integrators/npt.py
torch_sim/integrators/nve.py
torch_sim/integrators/nvt.py
torch_sim/io.py
torch_sim/math.py
torch_sim/models/__init__.py
torch_sim/models/fairchem.py
torch_sim/models/fairchem_legacy.py
torch_sim/models/graphpes.py
torch_sim/models/interface.py
torch_sim/models/lennard_jones.py
torch_sim/models/mace.py
torch_sim/models/mattersim.py
torch_sim/models/metatomic.py
torch_sim/models/morse.py
torch_sim/models/nequip_framework.py
torch_sim/models/orb.py
torch_sim/models/particle_life.py
torch_sim/models/sevennet.py
torch_sim/models/soft_sphere.py
torch_sim/monte_carlo.py
torch_sim/neighbors/__init__.py
torch_sim/neighbors/alchemiops.py
torch_sim/neighbors/standard.py
torch_sim/neighbors/torch_nl.py
torch_sim/neighbors/vesin.py
torch_sim/optimizers/__init__.py
torch_sim/optimizers/cell_filters.py
torch_sim/optimizers/fire.py
torch_sim/optimizers/gradient_descent.py
torch_sim/optimizers/state.py
torch_sim/properties/__init__.py
torch_sim/properties/correlations.py
torch_sim/py.typed
torch_sim/quantities.py
torch_sim/runners.py
torch_sim/state.py
torch_sim/trajectory.py
torch_sim/transforms.py
torch_sim/typing.py
torch_sim/units.py
torch_sim/workflows/__init__.py
torch_sim/workflows/a2c.py
torch_sim/workflows/readme.md
torch_sim_atomistic-0.5.1.dist-info/WHEEL
torch_sim_atomistic-0.5.1.dist-info/METADATA
torch_sim_atomistic-0.5.1.dist-info/RECORD
